deepdialog/__init__.py
deepdialog/component/__init__.py
deepdialog/component/base.py
deepdialog/component/decoder.py
deepdialog/component/discriminator.py
deepdialog/component/encoder.py
deepdialog/component/inference_net.py
deepdialog/data_handler/__init__.py
deepdialog/data_handler/data_utils.py
deepdialog/data_handler/dataloader.py
deepdialog/data_handler/dataset.py
deepdialog/distribution/__init__.py
deepdialog/distribution/distribution.py
deepdialog/evaluation/__init__.py
deepdialog/evaluation/dist_metric.py
deepdialog/evaluation/entropy.py
deepdialog/evaluation/property.py
deepdialog/evaluation/similarity.py
deepdialog/framework/__init__.py
deepdialog/framework/dialog_framework.py
deepdialog/model/__init__.py
deepdialog/model/base_model.py
deepdialog/model/hdgm/__init__.py
deepdialog/model/hdgm/hdgm.py
deepdialog/model/hred/__init__.py
deepdialog/model/hred/hred.py
deepdialog/model/kgcvae/__init__.py
deepdialog/model/kgcvae/kgcvae.py
deepdialog/model/kgcvae/kgcvae_runner.py
deepdialog/model/kgcvae/kgcvae_wrapper.py
deepdialog/model/seq2seq/__init__.py
deepdialog/model/seq2seq/seq2seq.py
deepdialog/model/vhred/__init__.py
deepdialog/model/vhred/vhred.py
deepdialog/model/vhred/vhred_runner.py
deepdialog/model/vhred/vhred_wrapper.py
deepdialog/utils/__init__.py
deepdialog/utils/attention_builder.py
deepdialog/utils/register.py
deepdialog/utils/rnn_builder.py
deepdialog/visualization/__init__.py
deepdialog/visualization/compare.py
deepdialog/visualization/heatmap.py
python_deepdialog-0.0.2.dist-info/METADATA
python_deepdialog-0.0.2.dist-info/WHEEL
python_deepdialog-0.0.2.dist-info/top_level.txt
python_deepdialog-0.0.2.dist-info/RECORD
